aiormq/__init__.py
aiormq/abc.py
aiormq/auth.py
aiormq/base.py
aiormq/channel.py
aiormq/connection.py
aiormq/exceptions.py
aiormq/py.typed
aiormq/tools.py
aiormq/types.py
aiormq-6.9.1.dist-info/COPYING
aiormq-6.9.1.dist-info/METADATA
aiormq-6.9.1.dist-info/WHEEL
aiormq-6.9.1.dist-info/RECORD
