Metadata-Version: 2.3
Name: aiormq
Version: 6.9.1
Summary: Pure python AMQP asynchronous client library
License: Apache-2.0
Keywords: rabbitmq,asyncio,amqp,amqp 0.9.1,driver,pamqp
Author: Dmitry Orlov
Author-email: me@mosquito.su
Requires-Python: >=3.10,<4.0
Classifier: Development Status :: 5 - Production/Stable
Classifier: Intended Audience :: Developers
Classifier: License :: OSI Approved :: Apache Software License
Classifier: Natural Language :: English
Classifier: Operating System :: MacOS
Classifier: Operating System :: Microsoft
Classifier: Operating System :: POSIX
Classifier: Programming Language :: Python
Classifier: Programming Language :: Python :: 3
Classifier: Programming Language :: Python :: 3.10
Classifier: Programming Language :: Python :: 3.11
Classifier: Programming Language :: Python :: 3.12
Classifier: Programming Language :: Python :: 3.13
Classifier: Programming Language :: Python :: 3 :: Only
Classifier: Programming Language :: Python :: 3.14
Classifier: Programming Language :: Python :: Implementation :: CPython
Classifier: Programming Language :: Python :: Implementation :: PyPy
Classifier: Topic :: Internet
Classifier: Topic :: Software Development
Classifier: Topic :: Software Development :: Libraries
Classifier: Topic :: System :: Clustering
Requires-Dist: pamqp (==3.3.0)
Requires-Dist: yarl
Project-URL: Documentation, https://github.com/mosquito/aiormq/blob/master/README.rst
Project-URL: Homepage, https://github.com/mosquito/aiormq
Project-URL: Source, https://github.com/mosquito/aiormq
Project-URL: Tracker, https://github.com/mosquito/aiormq/issues
